zoink/__init__.py
zoink-0.0.1.dist-info/LICENSE.txt
zoink-0.0.1.dist-info/METADATA
zoink-0.0.1.dist-info/WHEEL
zoink-0.0.1.dist-info/entry_points.txt
zoink-0.0.1.dist-info/RECORD
